jk_treetaggerwrapper
