Metadata-Version: 1.1
Name: jk-treetaggerwrapper
Version: 0.2018.12.19.2
Summary: This python module provides a wrapper around treetagger.
Home-page: https://github.com/jkpubsrc/python-module-jk-treetaggerwrapper
Author: Jürgen Knauth
Author-email: pubsrc@binary-overflow.de
License: Apache 2.0
Download-URL: https://github.com/jkpubsrc/python-module-jk-treetaggerwrapper/tarball/0.2018.12.19.2
Keywords: treetagger,pos-tagging
Platform: UNKNOWN
Classifier: Development Status :: 5 - Production/Stable
Classifier: Programming Language :: Python :: 3.5
Classifier: License :: OSI Approved :: Apache Software License
